{
  "data": [
    {
      "provider": "Metro General",
      "claimCount": 185000,
      "rateRelativity": 185,
      "isOutlier": true,
      "severity": "high",
      "category": "High Rate"
    },
    {
      "provider": "City Medical",
      "claimCount": 132000,
      "rateRelativity": 95,
      "isOutlier": false,
      "severity": "low",
      "category": "Normal"
    },
    {
      "provider": "Regional Health",
      "claimCount": 238000,
      "rateRelativity": 110,
      "isOutlier": false,
      "severity": "low",
      "category": "Normal"
    },
    {
      "provider": "University Hospital",
      "claimCount": 86500,
      "rateRelativity": 165,
      "isOutlier": true,
      "severity": "medium",
      "category": "High Rate"
    },
    {
      "provider": "Community Care",
      "claimCount": 254000,
      "rateRelativity": 88,
      "isOutlier": false,
      "severity": "low",
      "category": "Normal"
    },
    {
      "provider": "Specialty Center",
      "claimCount": 49500,
      "rateRelativity": 195,
      "isOutlier": true,
      "severity": "high",
      "category": "High Rate"
    },
    {
      "provider": "Valley Medical",
      "claimCount": 156000,
      "rateRelativity": 125,
      "isOutlier": false,
      "severity": "low",
      "category": "Normal"
    },
    {
      "provider": "Downtown Clinic",
      "claimCount": 37000,
      "rateRelativity": 75,
      "isOutlier": true,
      "severity": "medium",
      "category": "Low Rate"
    },
    {
      "provider": "Suburban Hospital",
      "claimCount": 168000,
      "rateRelativity": 115,
      "isOutlier": false,
      "severity": "low",
      "category": "Normal"
    },
    {
      "provider": "Academic Medical",
      "claimCount": 295000,
      "rateRelativity": 145,
      "isOutlier": true,
      "severity": "medium",
      "category": "High Rate"
    },
    {
      "provider": "Family Health",
      "claimCount": 115000,
      "rateRelativity": 105,
      "isOutlier": false,
      "severity": "low",
      "category": "Normal"
    },
    {
      "provider": "Emergency Care",
      "claimCount": 61500,
      "rateRelativity": 220,
      "isOutlier": true,
      "severity": "high",
      "category": "High Rate"
    },
    {
      "provider": "Wellness Center",
      "claimCount": 148000,
      "rateRelativity": 92,
      "isOutlier": false,
      "severity": "low",
      "category": "Normal"
    },
    {
      "provider": "Cardiac Institute",
      "claimCount": 98500,
      "rateRelativity": 175,
      "isOutlier": true,
      "severity": "high",
      "category": "High Rate"
    },
    {
      "provider": "Orthopedic Clinic",
      "claimCount": 74000,
      "rateRelativity": 155,
      "isOutlier": true,
      "severity": "medium",
      "category": "High Rate"
    }
  ]
}
